MANIFEST.in
README.md
setup.cfg
setup.py
wp_honeypot/__init__.py
wp_honeypot/admin.py
wp_honeypot/apps.py
wp_honeypot/models.py
wp_honeypot/urls.py
wp_honeypot/views.py
wp_honeypot.egg-info/PKG-INFO
wp_honeypot.egg-info/SOURCES.txt
wp_honeypot.egg-info/dependency_links.txt
wp_honeypot.egg-info/requires.txt
wp_honeypot.egg-info/top_level.txt
wp_honeypot/migrations/0001_initial.py
wp_honeypot/migrations/__init__.py
wp_honeypot/static/.DS_Store
wp_honeypot/static/css/wordpress.css
wp_honeypot/static/css/images/wordpress-logo.svg
wp_honeypot/static/wp-includes/.DS_Store
wp_honeypot/static/wp-includes/fonts/dashicons.eot
wp_honeypot/templates/wp_honeypot_login.html